[{"experienceUid":"671955b5b90fba279a8acc76","variants":[{"name":"Kiosk","__type":"SegmentedVariant","audiences":["671955b26b4ce91071b62c1e"],"audienceCombinationType":"AND","shortUid":"0"}],"status":"ACTIVE","createdBy":"blt4aabe76cbc5c8676","updatedBy":"blt4aabe76cbc5c8676","createdAt":"2024-10-23T19:59:49.196Z","updatedAt":"2024-10-23T19:59:49.672Z","firstActivatedAt":"2024-10-23T19:59:49.672Z","versionNumber":1,"uid":"671955b5b90fba279a8acc7b","createdByUserName":"Muhammed Constantino","updatedByUserName":"Muhammed Constantino"}]